MarkupSafe-3.0.0.dev0.dist-info/LICENSE.txt
MarkupSafe-3.0.0.dev0.dist-info/METADATA
MarkupSafe-3.0.0.dev0.dist-info/RECORD
MarkupSafe-3.0.0.dev0.dist-info/WHEEL
MarkupSafe-3.0.0.dev0.dist-info/top_level.txt
markupsafe/_speedups.c
markupsafe/_native.py
markupsafe/_speedups.pyi
markupsafe/_speedups.cpython-39-aarch64-linux-gnu.so
markupsafe/__init__.py
markupsafe/py.typed
