Metadata-Version: 2.1
Name: MarkupSafe
Version: 3.0.0.dev0
Summary: Safely add untrusted strings to HTML/XML markup.
Maintainer-email: Pallets <contact@palletsprojects.com>
License: Copyright 2010 Pallets
Project-URL: Donate, https://palletsprojects.com/donate
Project-URL: Documentation, https://markupsafe.palletsprojects.com/
Project-URL: Changes, https://markupsafe.palletsprojects.com/changes/
Project-URL: Source, https://github.com/pallets/markupsafe/
Project-URL: Chat, https://discord.gg/pallets
Classifier: Development Status :: 5 - Production/Stable
Classifier: Environment :: Web Environment
Classifier: Intended Audience :: Developers
Classifier: License :: OSI Approved :: BSD License
Classifier: Operating System :: OS Independent
Classifier: Programming Language :: Python
Classifier: Topic :: Internet :: WWW/HTTP :: Dynamic Content
Classifier: Topic :: Text Processing :: Markup :: HTML
Classifier: Typing :: Typed
Requires-Python: >=3.9
License-File: LICENSE.txt
